rssdk-3.19.dist-info/WHEEL
rssdk-3.19.dist-info/LICENSE-3RD-PARTY.txt
rssdk-3.19.dist-info/LICENSE
rssdk-3.19.dist-info/top_level.txt
rssdk-3.19.dist-info/RECORD
rssdk-3.19.dist-info/METADATA
rssdk/py.typed
rssdk/rssdk.cpython-311-i386-linux-gnu.so
rssdk/rssdk.pyi
rssdk/__init__.py
