Metadata-Version: 2.1
Name: rssdk
Version: 3.19
Summary: Rugged Science SDK Python Bindings
Author-email: Timothy Lassiter <tim.lassiter@ruggedscience.com>
License: MIT License
Project-URL: homepage, https://github.com/RuggedScience/SDK/tree/main/extras/python
Project-URL: documentation, https://github.com/RuggedScience/SDK/tree/main/extras/python
Project-URL: repository, https://github.com/RuggedScience/SDK/tree/main/extras/python
Keywords: rssdk,rsdio,rspoe,cmake
Classifier: Development Status :: 3 - Alpha
Classifier: Intended Audience :: Developers
Classifier: Topic :: Software Development :: Build Tools
Classifier: License :: OSI Approved :: MIT License
Classifier: Operating System :: OS Independent
Classifier: Programming Language :: Cython
Classifier: Programming Language :: C
Classifier: Programming Language :: Python :: Implementation :: CPython
Classifier: Topic :: Software Development :: Libraries
Classifier: Topic :: Utilities
Requires-Python: >=3.7
License-File: LICENSE
License-File: LICENSE-3RD-PARTY.txt
